hypixelaPY/__init__.py
hypixelaPY/client.py
hypixelaPY/exceptions.py
hypixelaPY/hypixel.py
hypixelaPY/mojang.py
hypixelaPY/utils.py
hypixelaPY/objects/__init__.py
hypixelaPY/objects/bedwars.py
hypixelaPY/objects/blitz.py
hypixelaPY/objects/duels.py
hypixelaPY/objects/guild.py
hypixelaPY/objects/leaderboards.py
hypixelaPY/objects/objects.py
hypixelaPY/objects/quake.py
hypixelaPY/objects/skywars.py
hypixelaPY/objects/stats.py
hypixelaPY-1.7.1.dist-info/LICENSE
hypixelaPY-1.7.1.dist-info/METADATA
hypixelaPY-1.7.1.dist-info/WHEEL
hypixelaPY-1.7.1.dist-info/top_level.txt
hypixelaPY-1.7.1.dist-info/RECORD
