Metadata-Version: 2.1
Name: hypixelaPY
Version: 1.7.1
Summary: An API wrapper for the Hypixel API
Home-page: https://github.com/myerfire/hypixelaPY
Author: myerfire
Author-email: realmyerfire@gmail.com
License: UNKNOWN
Platform: UNKNOWN
Classifier: Programming Language :: Python :: 3
Classifier: License :: OSI Approved :: MIT License
Classifier: Operating System :: OS Independent
Requires-Python: >=3.6
